CHANGES.txt
MANIFEST.in
README.md
setup.py
pyramid_mustache/__init__.py
pyramid_mustache.egg-info/PKG-INFO
pyramid_mustache.egg-info/SOURCES.txt
pyramid_mustache.egg-info/dependency_links.txt
pyramid_mustache.egg-info/entry_points.txt
pyramid_mustache.egg-info/not-zip-safe
pyramid_mustache.egg-info/requires.txt
pyramid_mustache.egg-info/top_level.txt