Metadata-Version: 1.1
Name: pyramid-mustache
Version: 0.3.1
Summary: pyramid_mustache
Home-page: http://github.com/eventray/pyramid_mustache
Author: John Anderson
Author-email: sontek@gmail.com
License: UNKNOWN
Keywords: web pyramid pylons
Platform: UNKNOWN
Classifier: Programming Language :: Python
Classifier: Framework :: Pylons
Classifier: Topic :: Internet :: WWW/HTTP
Classifier: Topic :: Internet :: WWW/HTTP :: WSGI :: Application
